AUTHORS.rst
CONTRIBUTING.rst
HISTORY.rst
LICENSE
MANIFEST.in
README.rst
pyproject.toml
setup.py
estats/__init__.py
estats/catalog.py
estats/likelihood.py
estats/map.py
estats/summary.py
estats/utils.py
estats.egg-info/PKG-INFO
estats.egg-info/SOURCES.txt
estats.egg-info/dependency_links.txt
estats.egg-info/not-zip-safe
estats.egg-info/requires.txt
estats.egg-info/top_level.txt
estats/stats/CLs.py
estats/stats/CrossCLs.py
estats/stats/CrossMinkowski.py
estats/stats/CrossPeaks.py
estats/stats/CrossShearCLs.py
estats/stats/CrossStarletL1Norm.py
estats/stats/CrossStarletL1NormDi.py
estats/stats/CrossStarletMinkowski.py
estats/stats/CrossStarletMinkowskiDi.py
estats/stats/CrossStarletPeaks.py
estats/stats/CrossStarletPeaksDi.py
estats/stats/CrossStarletVoids.py
estats/stats/CrossStarletVoidsDi.py
estats/stats/CrossVoids.py
estats/stats/Fulltest.py
estats/stats/Minkowski.py
estats/stats/Peaks.py
estats/stats/ShearCLs.py
estats/stats/Voids.py
estats/stats/__init__.py