Metadata-Version: 2.1
Name: estats
Version: 3.1.3
Summary: The building blocks of the Non-Gaussian Statistics Framework
Home-page: https://cosmo-docs.phys.ethz.ch/estats
Author: Dominik Zuercher
Author-email: dominikz@phys.ethz.ch
License: MIT License
Keywords: estats
Classifier: Development Status :: 4 - Beta
Classifier: Intended Audience :: Science/Research
Classifier: Intended Audience :: Developers
Classifier: License :: OSI Approved :: MIT License
Classifier: Natural Language :: English
Classifier: Programming Language :: Python :: 3.10
License-File: LICENSE
License-File: AUTHORS.rst
